icesugar_pro/src/fm_demod.sv
module fm_demod (
    input logic clk,
    input logic rst,
    input logic signed [15:0] i_in,
    input logic signed [15:0] q_in,
    input logic in_valid,

    output logic signed [7:0] audio_out,
    output logic audio_valid
);

logic signed [15:0] i_prev, q_prev;
logic signed [31:0] cross1, cross2;
logic signed [32:0] demod_raw;
logic signed [15:0] demod_scaled;

localparam DE_SHIFT = 2;
logic signed [15:0] de_state;

always_ff @(posedge clk or posedge rst) begin
    if (rst) begin
        i_prev <= '0;
        q_prev <= '0;
        cross1 <= '0;
        cross2 <= '0;
        demod_raw <= '0;
        demod_scaled <= '0;
        de_state <= '0;
        audio_out <= '0;
        audio_valid <= 1'b0;
    end else begin
        audio_valid <= 1'b0;
        if (in_valid) begin
            cross1 <= i_prev * q_in;
            cross2 <= i_in * q_prev;
            demod_raw <= cross1 - cross2;

            demod_scaled <= demod_raw[23:8];

            de_state <= de_state
                        - (de_state >>> DE_SHIFT)
                        + (demod_scaled >>> DE_SHIFT);

            audio_out <= de_state[15:8];
            audio_valid <= 1'b1;

            i_prev <= i_in;
            q_prev <= q_in;
        end
    end
end

endmodule

icesugar_pro/tb/tb_fm_demod.sv
`timescale 1ns/1ps

module tb_fm_demod;

localparam CLK_PERIOD = 40;

logic clk, rst;
logic signed [15:0] i_in, q_in;
logic in_valid;
logic signed [7:0] audio_out;
logic audio_valid;

fm_demod dut (
    .clk (clk),
    .rst (rst),
    .i_in (i_in),
    .q_in (q_in),
    .in_valid (in_valid),
    .audio_out (audio_out),
    .audio_valid (audio_valid)
);

initial clk = 0;
always #(CLK_PERIOD/2) clk = ~clk;

integer errors = 0;

task automatic drive_sample(input logic signed [15:0] i_val,
                            input logic signed [15:0] q_val);
    begin
        @(posedge clk);
        i_in <= i_val;
        q_in <= q_val;
        in_valid <= 1'b1;
    end
endtask

initial begin
    $dumpfile("build/fm_demod.vcd");
    $dumpvars(0, tb_fm_demod);

    rst = 1'b1;
    i_in = '0;
    q_in = '0;
    in_valid = 1'b0;

    repeat (4) @(posedge clk);
    rst <= 1'b0;

    drive_sample(16'sd1000, 16'sd0);
    drive_sample(16'sd0, 16'sd1000);
    drive_sample(-16'sd1000, 16'sd0);
    drive_sample(16'sd0, -16'sd1000);

    @(posedge clk);
    in_valid <= 1'b0;

    repeat (6) @(posedge clk);

    if (audio_out === 8'sbx) begin
        $display("FAIL audio_out is X");
        errors++;
    end else begin
        $display("PASS audio_out is known");
    end

    if (audio_valid === 1'bx) begin
        $display("FAIL audio_valid is X");
        errors++;
    end else begin
        $display("PASS audio_valid is known");
    end

    if (errors == 0)
        $display("ALL TESTS PASSED");
    else
        $display("FAILED: %0d error(s)", errors);

    $finish;
end

initial begin
    #10_000_000;
    $display("TIMEOUT");
    $finish;
end

endmodule

icesugar_pro/build/fm_demod.vcd
$date
	Wed May 27 11:14:47 2026
$end
$version
	Icarus Verilog
$end
$timescale
	1ps
$end
$scope module tb_fm_demod $end
$var wire 1 ! audio_valid $end
$var wire 8 " audio_out [7:0] $end
$var parameter 32 # CLK_PERIOD $end
$var reg 1 $ clk $end
$var reg 16 % i_in [15:0] $end
$var reg 1 & in_valid $end
$var reg 16 ' q_in [15:0] $end
$var reg 1 ( rst $end
$var integer 32 ) errors [31:0] $end
$scope module dut $end
$var wire 1 $ clk $end
$var wire 16 * i_in [15:0] $end
$var wire 1 & in_valid $end
$var wire 16 + q_in [15:0] $end
$var wire 1 ( rst $end
$var parameter 32 , DE_SHIFT $end
$var reg 8 - audio_out [7:0] $end
$var reg 1 ! audio_valid $end
$var reg 32 . cross1 [31:0] $end
$var reg 32 / cross2 [31:0] $end
$var reg 16 0 de_state [15:0] $end
$var reg 33 1 demod_raw [32:0] $end
$var reg 16 2 demod_scaled [15:0] $end
$var reg 16 3 i_prev [15:0] $end
$var reg 16 4 q_prev [15:0] $end
$upscope $end
$scope task drive_sample $end
$upscope $end
$upscope $end
$enddefinitions $end
$comment Show the parameter values. $end
$dumpall
b10 ,
b101000 #
$end
#0
$dumpvars
b0 4
b0 3
b0 2
b0 1
b0 0
b0 /
b0 .
b0 -
b0 +
b0 *
b0 )
1(
b0 '
0&
b0 %
0$
b0 "
0!
$end
#20000
1$
#40000
0$
#60000
1$
#80000
0$
#100000
1$
#120000
0$
#140000
0(
1$
#160000
0$
#180000
1&
b1111101000 %
b1111101000 *
1$
#200000
0$
#220000
b1111101000 3
1!
b1111101000 '
b1111101000 +
b0 %
b0 *
1$
#240000
0$
#260000
b1111101000 4
b0 3
b11110100001001000000 .
1!
b0 '
b0 +
b1111110000011000 %
b1111110000011000 *
1$
#280000
0$
#300000
b0 4
b1111110000011000 3
b11110100001001000000 1
b11111111111100001011110111000000 /
b0 .
1!
b1111110000011000 '
b1111110000011000 +
b0 %
b0 *
1$
#320000
0$
#340000
b1111110000011000 4
b0 3
b111101000010 2
b0 /
b11110100001001000000 .
1!
0&
1$
#360000
0$
#380000
0!
1$
