icesugar_pro/src/color_lut.sv
module color_lut (
    input logic [7:0] magnitude,
    output logic [15:0] color
);

logic [7:0] r, g, b;

always_comb begin
    if (magnitude < 8'd32) begin
        r = 8'd0;
        g = 8'd0;
        b = {magnitude[4:0], 3'b000};
    end else if (magnitude < 8'd96) begin
        r = 8'd0;
        g = {magnitude[5:0], 2'b00};
        b = 8'd255;
    end else if (magnitude < 8'd160) begin
        r = {magnitude[5:0], 2'b00};
        g = 8'd255;
        b = 8'd255 - {magnitude[5:0], 2'b00};
    end else begin
        r = 8'd255;
        g = 8'd255 - {magnitude[5:0], 2'b00};
        b = 8'd0;
    end
    color = {r[7:3], g[7:2], b[7:3]};
end

endmodule

icesugar_pro/src/lcd.sv
module lcd (
    input logic rst,
    input logic pclk,
    input logic [2:0] mode,
    input logic [7:0] volume,
    input logic mute,
    input logic [7:0] dbg_rx_count,
    input logic [7:0] dbg_bin_count,
    input logic [7:0] dbg_last_mag,

    input logic [7:0] wf_magnitude,
    output logic [7:0] wf_bin,
    output logic [8:0] wf_row_age,

    output logic LCD_DE,
    output logic [4:0] LCD_R,
    output logic [5:0] LCD_G,
    output logic [4:0] LCD_B
);

logic [10:0] x;
logic [9:0] y;

localparam MODE_FM = 3'd0;
localparam MODE_ADSB = 3'd1;
localparam MODE_APT = 3'd2;
localparam MODE_DIAG = 3'd7;

// Timing
always_ff @(posedge pclk) begin
    if (rst) begin
        x <= 11'd0;
        y <= 10'd0;
    end else begin
        if (x < 11'd1055) begin
            x <= x + 11'd1;
        end else begin
            x <= 11'd0;
            y <= (y < 10'd524) ? y + 10'd1 : 10'd0;
        end
    end
end

// Waterfall lookup
logic [7:0] bin_req;
logic [7:0] display_bin;
logic [8:0] row_age_req;
logic in_wf;
logic [22:0] bin_product;

always_comb begin
    in_wf = (mode == MODE_FM) && (x < 11'd768) && (y < 10'd360);
    bin_product = 23'(x) * 23'd2731;
    display_bin = bin_product[20:13];
    bin_req = in_wf ? display_bin + 8'd128 : 8'd0;
    row_age_req = in_wf ? 9'(y) : 9'd0;
end

assign wf_bin = bin_req;
assign wf_row_age = row_age_req;

logic [15:0] wf_color;

color_lut u_lut (
    .magnitude (wf_magnitude),
    .color (wf_color)
);

logic prev_in_wf;
logic prev_active;
logic [15:0] bg_color;

always_ff @(posedge pclk)
    prev_in_wf <= in_wf && (x < 11'd800) && (y < 10'd480);

always_comb begin
    prev_active = (x > 11'd0 || y > 10'd0);
end

always_comb begin
    bg_color = 16'h0000;
    if (mode == MODE_FM) begin
        if (y >= 10'd372 && y < 10'd388 && x < {3'b000, volume})
            bg_color = mute ? 16'hf800 : 16'h07e0;
        else if (y >= 10'd396 && y < 10'd412 && x < 11'd96)
            bg_color = 16'h001f;
        else if (y >= 10'd420 && y < 10'd432 && x < {3'b000, dbg_rx_count})
            bg_color = 16'hf800;
        else if (y >= 10'd440 && y < 10'd452 && x < {3'b000, dbg_bin_count})
            bg_color = 16'hffe0;
        else if (y >= 10'd460 && y < 10'd472 && x < {3'b000, dbg_last_mag})
            bg_color = 16'h07ff;
    end else if (mode == MODE_ADSB) begin
        bg_color = ((x[5:0] == 6'd0) || (y[5:0] == 6'd0)) ? 16'h07e0 : 16'h0020;
    end else if (mode == MODE_APT) begin
        bg_color = y[5] ? 16'h39e7 : 16'h001f;
    end else if (mode == MODE_DIAG) begin
        bg_color = x[5] ? 16'hf800 : 16'h001f;
    end
end

always_comb begin
    if (!rst && x < 11'd800 && y < 10'd480) begin
        LCD_DE = 1'b1;
        if (prev_in_wf) begin
            LCD_R = wf_color[15:11];
            LCD_G = wf_color[10:5];
            LCD_B = wf_color[4:0];
        end else begin
            LCD_R = bg_color[15:11];
            LCD_G = bg_color[10:5];
            LCD_B = bg_color[4:0];
        end
    end else begin
        LCD_DE = 1'b0;
        LCD_R = 5'd0;
        LCD_G = 6'd0;
        LCD_B = 5'd0;
    end
end

endmodule

icesugar_pro/tb/tb_lcd.sv
`timescale 1ns/1ps

module tb_lcd;

localparam CLK_PERIOD = 40;

logic pclk, rst;
logic [7:0] wf_magnitude;
logic [7:0] wf_bin;
logic [8:0] wf_row_age;
logic LCD_DE;
logic [4:0] LCD_R;
logic [5:0] LCD_G;
logic [4:0] LCD_B;

lcd dut (
    .rst (rst),
    .pclk (pclk),
    .mode (3'd0),
    .volume (8'hff),
    .mute (1'b0),
    .dbg_rx_count (8'd0),
    .dbg_bin_count (8'd0),
    .dbg_last_mag (8'd0),
    .wf_magnitude (wf_magnitude),
    .wf_bin (wf_bin),
    .wf_row_age (wf_row_age),
    .LCD_DE (LCD_DE),
    .LCD_R (LCD_R),
    .LCD_G (LCD_G),
    .LCD_B (LCD_B)
);

initial pclk = 0;
always #(CLK_PERIOD/2) pclk = ~pclk;

integer errors = 0;

initial begin
    $dumpfile("build/lcd.vcd");
    $dumpvars(0, tb_lcd);

    rst = 1'b1;
    wf_magnitude = 8'd128;

    repeat (4) @(posedge pclk);
    rst = 1'b0;

    wait (dut.x == 11'd383 && dut.y == 10'd0);
    #1;

    if (wf_bin !== 8'd255) begin
        $display("FAIL x=383 bin: expected 255 got %0d", wf_bin);
        errors++;
    end else begin
        $display("PASS x=383 bin = 255");
    end

    wait (dut.x == 11'd384 && dut.y == 10'd0);
    #1;

    if (wf_bin !== 8'd0) begin
        $display("FAIL x=384 bin: expected 0 got %0d", wf_bin);
        errors++;
    end else begin
        $display("PASS x=384 bin = 0");
    end

    wait (dut.x == 11'd767 && dut.y == 10'd0);
    #1;

    if (wf_bin !== 8'd127) begin
        $display("FAIL x=767 bin: expected 127 got %0d", wf_bin);
        errors++;
    end else begin
        $display("PASS x=767 bin = 127");
    end

    wait (dut.x == 11'd768 && dut.y == 10'd0);
    #1;

    if (wf_bin !== 8'd0) begin
        $display("FAIL x=768 bin: expected 0 got %0d", wf_bin);
        errors++;
    end else begin
        $display("PASS x=768 outside waterfall");
    end

    if (errors == 0)
        $display("ALL TESTS PASSED");
    else
        $display("FAILED: %0d error(s)", errors);

    $finish;
end

initial begin
    #10_000_000;
    $display("TIMEOUT");
    $finish;
end

endmodule

icesugar_pro/build/lcd.vcd
$date
	Wed May 27 11:14:47 2026
$end
$version
	Icarus Verilog
$end
$timescale
	1ps
$end
$scope module tb_lcd $end
$var wire 9 ! wf_row_age [8:0] $end
$var wire 8 " wf_bin [7:0] $end
$var wire 5 # LCD_R [4:0] $end
$var wire 6 $ LCD_G [5:0] $end
$var wire 1 % LCD_DE $end
$var wire 5 & LCD_B [4:0] $end
$var parameter 32 ' CLK_PERIOD $end
$var reg 1 ( pclk $end
$var reg 1 ) rst $end
$var reg 8 * wf_magnitude [7:0] $end
$var integer 32 + errors [31:0] $end
$scope module dut $end
$var wire 8 , dbg_bin_count [7:0] $end
$var wire 8 - dbg_last_mag [7:0] $end
$var wire 8 . dbg_rx_count [7:0] $end
$var wire 3 / mode [2:0] $end
$var wire 1 0 mute $end
$var wire 1 ( pclk $end
$var wire 1 ) rst $end
$var wire 8 1 volume [7:0] $end
$var wire 8 2 wf_bin [7:0] $end
$var wire 8 3 wf_magnitude [7:0] $end
$var wire 9 4 wf_row_age [8:0] $end
$var wire 16 5 wf_color [15:0] $end
$var parameter 3 6 MODE_ADSB $end
$var parameter 3 7 MODE_APT $end
$var parameter 3 8 MODE_DIAG $end
$var parameter 3 9 MODE_FM $end
$var reg 5 : LCD_B [4:0] $end
$var reg 1 % LCD_DE $end
$var reg 6 ; LCD_G [5:0] $end
$var reg 5 < LCD_R [4:0] $end
$var reg 16 = bg_color [15:0] $end
$var reg 23 > bin_product [22:0] $end
$var reg 8 ? bin_req [7:0] $end
$var reg 8 @ display_bin [7:0] $end
$var reg 1 A in_wf $end
$var reg 1 B prev_active $end
$var reg 1 C prev_in_wf $end
$var reg 9 D row_age_req [8:0] $end
$var reg 11 E x [10:0] $end
$var reg 10 F y [9:0] $end
$scope module u_lut $end
$var wire 8 G magnitude [7:0] $end
$var reg 8 H b [7:0] $end
$var reg 16 I color [15:0] $end
$var reg 8 J g [7:0] $end
$var reg 8 K r [7:0] $end
$upscope $end
$upscope $end
$upscope $end
$enddefinitions $end
$comment Show the parameter values. $end
$dumpall
b0 9
b111 8
b10 7
b1 6
b101000 '
$end
#0
$dumpvars
b0 K
b11111111 J
b11111111111 I
b11111111 H
b10000000 G
bx F
bx E
bx D
xC
xB
xA
bx @
bx ?
bx >
b0 =
b0 <
b0 ;
b0 :
b11111111111 5
bx 4
b10000000 3
bx 2
b11111111 1
00
b0 /
b0 .
b0 -
b0 ,
b0 +
b10000000 *
1)
0(
b0 &
0%
b0 $
b0 #
bx "
bx !
$end
#20000
0B
b0 !
b0 4
b0 D
b10000000 "
b10000000 2
b10000000 ?
b0 @
b0 >
1A
b0 F
b0 E
1(
#40000
0(
#60000
1C
1(
#80000
0(
#100000
1(
#120000
0(
#140000
b11111 &
b11111 :
b111111 $
b111111 ;
1%
0)
1(
#160000
0(
#180000
1B
b101010101011 >
b1 E
1(
#200000
0(
#220000
b1010101010110 >
b10 E
1(
#240000
0(
#260000
b10000001 "
b10000001 2
b10000001 ?
b1 @
b10000000000001 >
b11 E
1(
#280000
0(
#300000
b10101010101100 >
b100 E
1(
#320000
0(
#340000
b11010101010111 >
b101 E
1(
#360000
0(
#380000
b10000010 "
b10000010 2
b10000010 ?
b10 @
b100000000000010 >
b110 E
1(
#400000
0(
#420000
b100101010101101 >
b111 E
1(
#440000
0(
#460000
b101010101011000 >
b1000 E
1(
#480000
0(
#500000
b10000011 "
b10000011 2
b10000011 ?
b11 @
b110000000000011 >
b1001 E
1(
#520000
0(
#540000
b110101010101110 >
b1010 E
1(
#560000
0(
#580000
b111010101011001 >
b1011 E
1(
#600000
0(
#620000
b10000100 "
b10000100 2
b10000100 ?
b100 @
b1000000000000100 >
b1100 E
1(
#640000
0(
#660000
b1000101010101111 >
b1101 E
1(
#680000
0(
#700000
b1001010101011010 >
b1110 E
1(
#720000
0(
#740000
b10000101 "
b10000101 2
b10000101 ?
b101 @
b1010000000000101 >
b1111 E
1(
#760000
0(
#780000
b1010101010110000 >
b10000 E
1(
#800000
0(
#820000
b1011010101011011 >
b10001 E
1(
#840000
0(
#860000
b10000110 "
b10000110 2
b10000110 ?
b110 @
b1100000000000110 >
b10010 E
1(
#880000
0(
#900000
b1100101010110001 >
b10011 E
1(
#920000
0(
#940000
b1101010101011100 >
b10100 E
1(
#960000
0(
#980000
b10000111 "
b10000111 2
b10000111 ?
b111 @
b1110000000000111 >
b10101 E
1(
#1000000
0(
#1020000
b1110101010110010 >
b10110 E
1(
#1040000
0(
#1060000
b1111010101011101 >
b10111 E
1(
#1080000
0(
#1100000
b10001000 "
b10001000 2
b10001000 ?
b1000 @
b10000000000001000 >
b11000 E
1(
#1120000
0(
#1140000
b10000101010110011 >
b11001 E
1(
#1160000
0(
#1180000
b10001010101011110 >
b11010 E
1(
#1200000
0(
#1220000
b10001001 "
b10001001 2
b10001001 ?
b1001 @
b10010000000001001 >
b11011 E
1(
#1240000
0(
#1260000
b10010101010110100 >
b11100 E
1(
#1280000
0(
#1300000
b10011010101011111 >
b11101 E
1(
#1320000
0(
#1340000
b10001010 "
b10001010 2
b10001010 ?
b1010 @
b10100000000001010 >
b11110 E
1(
#1360000
0(
#1380000
b10100101010110101 >
b11111 E
1(
#1400000
0(
#1420000
b10101010101100000 >
b100000 E
1(
#1440000
0(
#1460000
b10001011 "
b10001011 2
b10001011 ?
b1011 @
b10110000000001011 >
b100001 E
1(
#1480000
0(
#1500000
b10110101010110110 >
b100010 E
1(
#1520000
0(
#1540000
b10111010101100001 >
b100011 E
1(
#1560000
0(
#1580000
b10001100 "
b10001100 2
b10001100 ?
b1100 @
b11000000000001100 >
b100100 E
1(
#1600000
0(
#1620000
b11000101010110111 >
b100101 E
1(
#1640000
0(
#1660000
b11001010101100010 >
b100110 E
1(
#1680000
0(
#1700000
b10001101 "
b10001101 2
b10001101 ?
b1101 @
b11010000000001101 >
b100111 E
1(
#1720000
0(
#1740000
b11010101010111000 >
b101000 E
1(
#1760000
0(
#1780000
b11011010101100011 >
b101001 E
1(
#1800000
0(
#1820000
b10001110 "
b10001110 2
b10001110 ?
b1110 @
b11100000000001110 >
b101010 E
1(
#1840000
0(
#1860000
b11100101010111001 >
b101011 E
1(
#1880000
0(
#1900000
b11101010101100100 >
b101100 E
1(
#1920000
0(
#1940000
b10001111 "
b10001111 2
b10001111 ?
b1111 @
b11110000000001111 >
b101101 E
1(
#1960000
0(
#1980000
b11110101010111010 >
b101110 E
1(
#2000000
0(
#2020000
b11111010101100101 >
b101111 E
1(
#2040000
0(
#2060000
b10010000 "
b10010000 2
b10010000 ?
b10000 @
b100000000000010000 >
b110000 E
1(
#2080000
0(
#2100000
b100000101010111011 >
b110001 E
1(
#2120000
0(
#2140000
b100001010101100110 >
b110010 E
1(
#2160000
0(
#2180000
b10010001 "
b10010001 2
b10010001 ?
b10001 @
b100010000000010001 >
b110011 E
1(
#2200000
0(
#2220000
b100010101010111100 >
b110100 E
1(
#2240000
0(
#2260000
b100011010101100111 >
b110101 E
1(
#2280000
0(
#2300000
b10010010 "
b10010010 2
b10010010 ?
b10010 @
b100100000000010010 >
b110110 E
1(
#2320000
0(
#2340000
b100100101010111101 >
b110111 E
1(
#2360000
0(
#2380000
b100101010101101000 >
b111000 E
1(
#2400000
0(
#2420000
b10010011 "
b10010011 2
b10010011 ?
b10011 @
b100110000000010011 >
b111001 E
1(
#2440000
0(
#2460000
b100110101010111110 >
b111010 E
1(
#2480000
0(
#2500000
b100111010101101001 >
b111011 E
1(
#2520000
0(
#2540000
b10010100 "
b10010100 2
b10010100 ?
b10100 @
b101000000000010100 >
b111100 E
1(
#2560000
0(
#2580000
b101000101010111111 >
b111101 E
1(
#2600000
0(
#2620000
b101001010101101010 >
b111110 E
1(
#2640000
0(
#2660000
b10010101 "
b10010101 2
b10010101 ?
b10101 @
b101010000000010101 >
b111111 E
1(
#2680000
0(
#2700000
b101010101011000000 >
b1000000 E
1(
#2720000
0(
#2740000
b101011010101101011 >
b1000001 E
1(
#2760000
0(
#2780000
b10010110 "
b10010110 2
b10010110 ?
b10110 @
b101100000000010110 >
b1000010 E
1(
#2800000
0(
#2820000
b101100101011000001 >
b1000011 E
1(
#2840000
0(
#2860000
b101101010101101100 >
b1000100 E
1(
#2880000
0(
#2900000
b10010111 "
b10010111 2
b10010111 ?
b10111 @
b101110000000010111 >
b1000101 E
1(
#2920000
0(
#2940000
b101110101011000010 >
b1000110 E
1(
#2960000
0(
#2980000
b101111010101101101 >
b1000111 E
1(
#3000000
0(
#3020000
b10011000 "
b10011000 2
b10011000 ?
b11000 @
b110000000000011000 >
b1001000 E
1(
#3040000
0(
#3060000
b110000101011000011 >
b1001001 E
1(
#3080000
0(
#3100000
b110001010101101110 >
b1001010 E
1(
#3120000
0(
#3140000
b10011001 "
b10011001 2
b10011001 ?
b11001 @
b110010000000011001 >
b1001011 E
1(
#3160000
0(
#3180000
b110010101011000100 >
b1001100 E
1(
#3200000
0(
#3220000
b110011010101101111 >
b1001101 E
1(
#3240000
0(
#3260000
b10011010 "
b10011010 2
b10011010 ?
b11010 @
b110100000000011010 >
b1001110 E
1(
#3280000
0(
#3300000
b110100101011000101 >
b1001111 E
1(
#3320000
0(
#3340000
b110101010101110000 >
b1010000 E
1(
#3360000
0(
#3380000
b10011011 "
b10011011 2
b10011011 ?
b11011 @
b110110000000011011 >
b1010001 E
1(
#3400000
0(
#3420000
b110110101011000110 >
b1010010 E
1(
#3440000
0(
#3460000
b110111010101110001 >
b1010011 E
1(
#3480000
0(
#3500000
b10011100 "
b10011100 2
b10011100 ?
b11100 @
b111000000000011100 >
b1010100 E
1(
#3520000
0(
#3540000
b111000101011000111 >
b1010101 E
1(
#3560000
0(
#3580000
b111001010101110010 >
b1010110 E
1(
#3600000
0(
#3620000
b10011101 "
b10011101 2
b10011101 ?
b11101 @
b111010000000011101 >
b1010111 E
1(
#3640000
0(
#3660000
b111010101011001000 >
b1011000 E
1(
#3680000
0(
#3700000
b111011010101110011 >
b1011001 E
1(
#3720000
0(
#3740000
b10011110 "
b10011110 2
b10011110 ?
b11110 @
b111100000000011110 >
b1011010 E
1(
#3760000
0(
#3780000
b111100101011001001 >
b1011011 E
1(
#3800000
0(
#3820000
b111101010101110100 >
b1011100 E
1(
#3840000
0(
#3860000
b10011111 "
b10011111 2
b10011111 ?
b11111 @
b111110000000011111 >
b1011101 E
1(
#3880000
0(
#3900000
b111110101011001010 >
b1011110 E
1(
#3920000
0(
#3940000
b111111010101110101 >
b1011111 E
1(
#3960000
0(
#3980000
b10100000 "
b10100000 2
b10100000 ?
b100000 @
b1000000000000100000 >
b1100000 E
1(
#4000000
0(
#4020000
b1000000101011001011 >
b1100001 E
1(
#4040000
0(
#4060000
b1000001010101110110 >
b1100010 E
1(
#4080000
0(
#4100000
b10100001 "
b10100001 2
b10100001 ?
b100001 @
b1000010000000100001 >
b1100011 E
1(
#4120000
0(
#4140000
b1000010101011001100 >
b1100100 E
1(
#4160000
0(
#4180000
b1000011010101110111 >
b1100101 E
1(
#4200000
0(
#4220000
b10100010 "
b10100010 2
b10100010 ?
b100010 @
b1000100000000100010 >
b1100110 E
1(
#4240000
0(
#4260000
b1000100101011001101 >
b1100111 E
1(
#4280000
0(
#4300000
b1000101010101111000 >
b1101000 E
1(
#4320000
0(
#4340000
b10100011 "
b10100011 2
b10100011 ?
b100011 @
b1000110000000100011 >
b1101001 E
1(
#4360000
0(
#4380000
b1000110101011001110 >
b1101010 E
1(
#4400000
0(
#4420000
b1000111010101111001 >
b1101011 E
1(
#4440000
0(
#4460000
b10100100 "
b10100100 2
b10100100 ?
b100100 @
b1001000000000100100 >
b1101100 E
1(
#4480000
0(
#4500000
b1001000101011001111 >
b1101101 E
1(
#4520000
0(
#4540000
b1001001010101111010 >
b1101110 E
1(
#4560000
0(
#4580000
b10100101 "
b10100101 2
b10100101 ?
b100101 @
b1001010000000100101 >
b1101111 E
1(
#4600000
0(
#4620000
b1001010101011010000 >
b1110000 E
1(
#4640000
0(
#4660000
b1001011010101111011 >
b1110001 E
1(
#4680000
0(
#4700000
b10100110 "
b10100110 2
b10100110 ?
b100110 @
b1001100000000100110 >
b1110010 E
1(
#4720000
0(
#4740000
b1001100101011010001 >
b1110011 E
1(
#4760000
0(
#4780000
b1001101010101111100 >
b1110100 E
1(
#4800000
0(
#4820000
b10100111 "
b10100111 2
b10100111 ?
b100111 @
b1001110000000100111 >
b1110101 E
1(
#4840000
0(
#4860000
b1001110101011010010 >
b1110110 E
1(
#4880000
0(
#4900000
b1001111010101111101 >
b1110111 E
1(
#4920000
0(
#4940000
b10101000 "
b10101000 2
b10101000 ?
b101000 @
b1010000000000101000 >
b1111000 E
1(
#4960000
0(
#4980000
b1010000101011010011 >
b1111001 E
1(
#5000000
0(
#5020000
b1010001010101111110 >
b1111010 E
1(
#5040000
0(
#5060000
b10101001 "
b10101001 2
b10101001 ?
b101001 @
b1010010000000101001 >
b1111011 E
1(
#5080000
0(
#5100000
b1010010101011010100 >
b1111100 E
1(
#5120000
0(
#5140000
b1010011010101111111 >
b1111101 E
1(
#5160000
0(
#5180000
b10101010 "
b10101010 2
b10101010 ?
b101010 @
b1010100000000101010 >
b1111110 E
1(
#5200000
0(
#5220000
b1010100101011010101 >
b1111111 E
1(
#5240000
0(
#5260000
b1010101010110000000 >
b10000000 E
1(
#5280000
0(
#5300000
b10101011 "
b10101011 2
b10101011 ?
b101011 @
b1010110000000101011 >
b10000001 E
1(
#5320000
0(
#5340000
b1010110101011010110 >
b10000010 E
1(
#5360000
0(
#5380000
b1010111010110000001 >
b10000011 E
1(
#5400000
0(
#5420000
b10101100 "
b10101100 2
b10101100 ?
b101100 @
b1011000000000101100 >
b10000100 E
1(
#5440000
0(
#5460000
b1011000101011010111 >
b10000101 E
1(
#5480000
0(
#5500000
b1011001010110000010 >
b10000110 E
1(
#5520000
0(
#5540000
b10101101 "
b10101101 2
b10101101 ?
b101101 @
b1011010000000101101 >
b10000111 E
1(
#5560000
0(
#5580000
b1011010101011011000 >
b10001000 E
1(
#5600000
0(
#5620000
b1011011010110000011 >
b10001001 E
1(
#5640000
0(
#5660000
b10101110 "
b10101110 2
b10101110 ?
b101110 @
b1011100000000101110 >
b10001010 E
1(
#5680000
0(
#5700000
b1011100101011011001 >
b10001011 E
1(
#5720000
0(
#5740000
b1011101010110000100 >
b10001100 E
1(
#5760000
0(
#5780000
b10101111 "
b10101111 2
b10101111 ?
b101111 @
b1011110000000101111 >
b10001101 E
1(
#5800000
0(
#5820000
b1011110101011011010 >
b10001110 E
1(
#5840000
0(
#5860000
b1011111010110000101 >
b10001111 E
1(
#5880000
0(
#5900000
b10110000 "
b10110000 2
b10110000 ?
b110000 @
b1100000000000110000 >
b10010000 E
1(
#5920000
0(
#5940000
b1100000101011011011 >
b10010001 E
1(
#5960000
0(
#5980000
b1100001010110000110 >
b10010010 E
1(
#6000000
0(
#6020000
b10110001 "
b10110001 2
b10110001 ?
b110001 @
b1100010000000110001 >
b10010011 E
1(
#6040000
0(
#6060000
b1100010101011011100 >
b10010100 E
1(
#6080000
0(
#6100000
b1100011010110000111 >
b10010101 E
1(
#6120000
0(
#6140000
b10110010 "
b10110010 2
b10110010 ?
b110010 @
b1100100000000110010 >
b10010110 E
1(
#6160000
0(
#6180000
b1100100101011011101 >
b10010111 E
1(
#6200000
0(
#6220000
b1100101010110001000 >
b10011000 E
1(
#6240000
0(
#6260000
b10110011 "
b10110011 2
b10110011 ?
b110011 @
b1100110000000110011 >
b10011001 E
1(
#6280000
0(
#6300000
b1100110101011011110 >
b10011010 E
1(
#6320000
0(
#6340000
b1100111010110001001 >
b10011011 E
1(
#6360000
0(
#6380000
b10110100 "
b10110100 2
b10110100 ?
b110100 @
b1101000000000110100 >
b10011100 E
1(
#6400000
0(
#6420000
b1101000101011011111 >
b10011101 E
1(
#6440000
0(
#6460000
b1101001010110001010 >
b10011110 E
1(
#6480000
0(
#6500000
b10110101 "
b10110101 2
b10110101 ?
b110101 @
b1101010000000110101 >
b10011111 E
1(
#6520000
0(
#6540000
b1101010101011100000 >
b10100000 E
1(
#6560000
0(
#6580000
b1101011010110001011 >
b10100001 E
1(
#6600000
0(
#6620000
b10110110 "
b10110110 2
b10110110 ?
b110110 @
b1101100000000110110 >
b10100010 E
1(
#6640000
0(
#6660000
b1101100101011100001 >
b10100011 E
1(
#6680000
0(
#6700000
b1101101010110001100 >
b10100100 E
1(
#6720000
0(
#6740000
b10110111 "
b10110111 2
b10110111 ?
b110111 @
b1101110000000110111 >
b10100101 E
1(
#6760000
0(
#6780000
b1101110101011100010 >
b10100110 E
1(
#6800000
0(
#6820000
b1101111010110001101 >
b10100111 E
1(
#6840000
0(
#6860000
b10111000 "
b10111000 2
b10111000 ?
b111000 @
b1110000000000111000 >
b10101000 E
1(
#6880000
0(
#6900000
b1110000101011100011 >
b10101001 E
1(
#6920000
0(
#6940000
b1110001010110001110 >
b10101010 E
1(
#6960000
0(
#6980000
b10111001 "
b10111001 2
b10111001 ?
b111001 @
b1110010000000111001 >
b10101011 E
1(
#7000000
0(
#7020000
b1110010101011100100 >
b10101100 E
1(
#7040000
0(
#7060000
b1110011010110001111 >
b10101101 E
1(
#7080000
0(
#7100000
b10111010 "
b10111010 2
b10111010 ?
b111010 @
b1110100000000111010 >
b10101110 E
1(
#7120000
0(
#7140000
b1110100101011100101 >
b10101111 E
1(
#7160000
0(
#7180000
b1110101010110010000 >
b10110000 E
1(
#7200000
0(
#7220000
b10111011 "
b10111011 2
b10111011 ?
b111011 @
b1110110000000111011 >
b10110001 E
1(
#7240000
0(
#7260000
b1110110101011100110 >
b10110010 E
1(
#7280000
0(
#7300000
b1110111010110010001 >
b10110011 E
1(
#7320000
0(
#7340000
b10111100 "
b10111100 2
b10111100 ?
b111100 @
b1111000000000111100 >
b10110100 E
1(
#7360000
0(
#7380000
b1111000101011100111 >
b10110101 E
1(
#7400000
0(
#7420000
b1111001010110010010 >
b10110110 E
1(
#7440000
0(
#7460000
b10111101 "
b10111101 2
b10111101 ?
b111101 @
b1111010000000111101 >
b10110111 E
1(
#7480000
0(
#7500000
b1111010101011101000 >
b10111000 E
1(
#7520000
0(
#7540000
b1111011010110010011 >
b10111001 E
1(
#7560000
0(
#7580000
b10111110 "
b10111110 2
b10111110 ?
b111110 @
b1111100000000111110 >
b10111010 E
1(
#7600000
0(
#7620000
b1111100101011101001 >
b10111011 E
1(
#7640000
0(
#7660000
b1111101010110010100 >
b10111100 E
1(
#7680000
0(
#7700000
b10111111 "
b10111111 2
b10111111 ?
b111111 @
b1111110000000111111 >
b10111101 E
1(
#7720000
0(
#7740000
b1111110101011101010 >
b10111110 E
1(
#7760000
0(
#7780000
b1111111010110010101 >
b10111111 E
1(
#7800000
0(
#7820000
b11000000 "
b11000000 2
b11000000 ?
b1000000 @
b10000000000001000000 >
b11000000 E
1(
#7840000
0(
#7860000
b10000000101011101011 >
b11000001 E
1(
#7880000
0(
#7900000
b10000001010110010110 >
b11000010 E
1(
#7920000
0(
#7940000
b11000001 "
b11000001 2
b11000001 ?
b1000001 @
b10000010000001000001 >
b11000011 E
1(
#7960000
0(
#7980000
b10000010101011101100 >
b11000100 E
1(
#8000000
0(
#8020000
b10000011010110010111 >
b11000101 E
1(
#8040000
0(
#8060000
b11000010 "
b11000010 2
b11000010 ?
b1000010 @
b10000100000001000010 >
b11000110 E
1(
#8080000
0(
#8100000
b10000100101011101101 >
b11000111 E
1(
#8120000
0(
#8140000
b10000101010110011000 >
b11001000 E
1(
#8160000
0(
#8180000
b11000011 "
b11000011 2
b11000011 ?
b1000011 @
b10000110000001000011 >
b11001001 E
1(
#8200000
0(
#8220000
b10000110101011101110 >
b11001010 E
1(
#8240000
0(
#8260000
b10000111010110011001 >
b11001011 E
1(
#8280000
0(
#8300000
b11000100 "
b11000100 2
b11000100 ?
b1000100 @
b10001000000001000100 >
b11001100 E
1(
#8320000
0(
#8340000
b10001000101011101111 >
b11001101 E
1(
#8360000
0(
#8380000
b10001001010110011010 >
b11001110 E
1(
#8400000
0(
#8420000
b11000101 "
b11000101 2
b11000101 ?
b1000101 @
b10001010000001000101 >
b11001111 E
1(
#8440000
0(
#8460000
b10001010101011110000 >
b11010000 E
1(
#8480000
0(
#8500000
b10001011010110011011 >
b11010001 E
1(
#8520000
0(
#8540000
b11000110 "
b11000110 2
b11000110 ?
b1000110 @
b10001100000001000110 >
b11010010 E
1(
#8560000
0(
#8580000
b10001100101011110001 >
b11010011 E
1(
#8600000
0(
#8620000
b10001101010110011100 >
b11010100 E
1(
#8640000
0(
#8660000
b11000111 "
b11000111 2
b11000111 ?
b1000111 @
b10001110000001000111 >
b11010101 E
1(
#8680000
0(
#8700000
b10001110101011110010 >
b11010110 E
1(
#8720000
0(
#8740000
b10001111010110011101 >
b11010111 E
1(
#8760000
0(
#8780000
b11001000 "
b11001000 2
b11001000 ?
b1001000 @
b10010000000001001000 >
b11011000 E
1(
#8800000
0(
#8820000
b10010000101011110011 >
b11011001 E
1(
#8840000
0(
#8860000
b10010001010110011110 >
b11011010 E
1(
#8880000
0(
#8900000
b11001001 "
b11001001 2
b11001001 ?
b1001001 @
b10010010000001001001 >
b11011011 E
1(
#8920000
0(
#8940000
b10010010101011110100 >
b11011100 E
1(
#8960000
0(
#8980000
b10010011010110011111 >
b11011101 E
1(
#9000000
0(
#9020000
b11001010 "
b11001010 2
b11001010 ?
b1001010 @
b10010100000001001010 >
b11011110 E
1(
#9040000
0(
#9060000
b10010100101011110101 >
b11011111 E
1(
#9080000
0(
#9100000
b10010101010110100000 >
b11100000 E
1(
#9120000
0(
#9140000
b11001011 "
b11001011 2
b11001011 ?
b1001011 @
b10010110000001001011 >
b11100001 E
1(
#9160000
0(
#9180000
b10010110101011110110 >
b11100010 E
1(
#9200000
0(
#9220000
b10010111010110100001 >
b11100011 E
1(
#9240000
0(
#9260000
b11001100 "
b11001100 2
b11001100 ?
b1001100 @
b10011000000001001100 >
b11100100 E
1(
#9280000
0(
#9300000
b10011000101011110111 >
b11100101 E
1(
#9320000
0(
#9340000
b10011001010110100010 >
b11100110 E
1(
#9360000
0(
#9380000
b11001101 "
b11001101 2
b11001101 ?
b1001101 @
b10011010000001001101 >
b11100111 E
1(
#9400000
0(
#9420000
b10011010101011111000 >
b11101000 E
1(
#9440000
0(
#9460000
b10011011010110100011 >
b11101001 E
1(
#9480000
0(
#9500000
b11001110 "
b11001110 2
b11001110 ?
b1001110 @
b10011100000001001110 >
b11101010 E
1(
#9520000
0(
#9540000
b10011100101011111001 >
b11101011 E
1(
#9560000
0(
#9580000
b10011101010110100100 >
b11101100 E
1(
#9600000
0(
#9620000
b11001111 "
b11001111 2
b11001111 ?
b1001111 @
b10011110000001001111 >
b11101101 E
1(
#9640000
0(
#9660000
b10011110101011111010 >
b11101110 E
1(
#9680000
0(
#9700000
b10011111010110100101 >
b11101111 E
1(
#9720000
0(
#9740000
b11010000 "
b11010000 2
b11010000 ?
b1010000 @
b10100000000001010000 >
b11110000 E
1(
#9760000
0(
#9780000
b10100000101011111011 >
b11110001 E
1(
#9800000
0(
#9820000
b10100001010110100110 >
b11110010 E
1(
#9840000
0(
#9860000
b11010001 "
b11010001 2
b11010001 ?
b1010001 @
b10100010000001010001 >
b11110011 E
1(
#9880000
0(
#9900000
b10100010101011111100 >
b11110100 E
1(
#9920000
0(
#9940000
b10100011010110100111 >
b11110101 E
1(
#9960000
0(
#9980000
b11010010 "
b11010010 2
b11010010 ?
b1010010 @
b10100100000001010010 >
b11110110 E
1(
#10000000
0(
#10020000
b10100100101011111101 >
b11110111 E
1(
#10040000
0(
